<?xml version="1.0"?>
<!DOCTYPE ACTIONS SYSTEM "actions.dtd">

<ACTIONS>
	<ACTION NAME="isabelle.theories-panel">
		<CODE>
			wm.addDockableWindow("isabelle-theories");
		</CODE>
	</ACTION>
	<ACTION NAME="isabelle.timing-panel">
		<CODE>
			wm.addDockableWindow("isabelle-timing");
		</CODE>
	</ACTION>
	<ACTION NAME="isabelle.syslog-panel">
		<CODE>
			wm.addDockableWindow("isabelle-syslog");
		</CODE>
	</ACTION>
	<ACTION NAME="isabelle.documentation-panel">
		<CODE>
			wm.addDockableWindow("isabelle-documentation");
		</CODE>
	</ACTION>
	<ACTION NAME="isabelle.find-panel">
		<CODE>
			wm.addDockableWindow("isabelle-find");
		</CODE>
	</ACTION>
	<ACTION NAME="isabelle.sledgehammer-panel">
		<CODE>
			wm.addDockableWindow("isabelle-sledgehammer");
		</CODE>
	</ACTION>
	<ACTION NAME="isabelle.output-panel">
		<CODE>
			wm.addDockableWindow("isabelle-output");
		</CODE>
	</ACTION>
	<ACTION NAME="isabelle.raw-output-panel">
		<CODE>
			wm.addDockableWindow("isabelle-raw-output");
		</CODE>
	</ACTION>
	<ACTION NAME="isabelle.simp-trace-panel">
		<CODE>
			wm.addDockableWindow("isabelle-simp-trace");
		</CODE>
	</ACTION>
	<ACTION NAME="isabelle.protocol-panel">
		<CODE>
			wm.addDockableWindow("isabelle-protocol");
		</CODE>
	</ACTION>
	<ACTION NAME="isabelle.monitor-panel">
		<CODE>
			wm.addDockableWindow("isabelle-monitor");
		</CODE>
	</ACTION>
	<ACTION NAME="isabelle.symbols-panel">
		<CODE>
			wm.addDockableWindow("isabelle-symbols");
		</CODE>
	</ACTION>
	<ACTION NAME="isabelle.set-continuous-checking">
	  <CODE>
	    isabelle.jedit.Isabelle.set_continuous_checking();
	  </CODE>
	</ACTION>
	<ACTION NAME="isabelle.reset-continuous-checking">
	  <CODE>
	    isabelle.jedit.Isabelle.reset_continuous_checking();
	  </CODE>
	</ACTION>
	<ACTION NAME="isabelle.toggle-continuous-checking">
	  <CODE>
	    isabelle.jedit.Isabelle.toggle_continuous_checking();
	  </CODE>
	</ACTION>
	<ACTION NAME="isabelle.set-node-required">
	  <CODE>
	    isabelle.jedit.Isabelle.set_node_required(view);
	  </CODE>
	</ACTION>
	<ACTION NAME="isabelle.reset-node-required">
	  <CODE>
	    isabelle.jedit.Isabelle.reset_node_required(view);
	  </CODE>
	</ACTION>
	<ACTION NAME="isabelle.toggle-node-required">
	  <CODE>
	    isabelle.jedit.Isabelle.toggle_node_required(view);
	  </CODE>
	</ACTION>
	<ACTION NAME="isabelle.reset-font-size">
	  <CODE>
	    isabelle.jedit.Isabelle.reset_font_size(view);
	  </CODE>
	</ACTION>
	<ACTION NAME="isabelle.increase-font-size">
	  <CODE>
	    isabelle.jedit.Isabelle.increase_font_size(view);
	  </CODE>
	</ACTION>
	<ACTION NAME="isabelle.increase-font-size2">
	  <CODE>
	    isabelle.jedit.Isabelle.increase_font_size(view);
	  </CODE>
	</ACTION>
	<ACTION NAME="isabelle.decrease-font-size">
	  <CODE>
	    isabelle.jedit.Isabelle.decrease_font_size(view);
	  </CODE>
	</ACTION>
	<ACTION NAME="isabelle.decrease-font-size2">
	  <CODE>
	    isabelle.jedit.Isabelle.decrease_font_size(view);
	  </CODE>
	</ACTION>
	<ACTION NAME="isabelle.complete">
	  <CODE>
	    isabelle.jedit.Isabelle.complete(view);
	  </CODE>
	</ACTION>
	<ACTION NAME="isabelle.control-sub">
	  <CODE>
	    isabelle.jedit.Isabelle.control_sub(textArea);
	  </CODE>
	</ACTION>
	<ACTION NAME="isabelle.control-sup">
	  <CODE>
	    isabelle.jedit.Isabelle.control_sup(textArea);
	  </CODE>
	</ACTION>
	<ACTION NAME="isabelle.control-bold">
	  <CODE>
	    isabelle.jedit.Isabelle.control_bold(textArea);
	  </CODE>
	</ACTION>
	<ACTION NAME="isabelle.control-reset">
	  <CODE>
	    isabelle.jedit.Isabelle.control_reset(textArea);
	  </CODE>
	</ACTION>
	<ACTION NAME="isabelle.input-bsub">
	  <CODE>
	    isabelle.jedit.Isabelle.input_bsub(textArea);
	  </CODE>
	</ACTION>
	<ACTION NAME="isabelle.input-bsup">
	  <CODE>
	    isabelle.jedit.Isabelle.input_bsup(textArea);
	  </CODE>
	</ACTION>
</ACTIONS>
